LICENSE
MANIFEST.in
README.rst
setup.cfg
setup.py
versioneer.py
artellapipe/__init__.py
artellapipe/config/__init__.py
artellapipe/config/__version__.py
artellapipe/config/_version.py
artellapipe/config/development/artellapipe-assets.yml
artellapipe/config/development/artellapipe-dccs-maya.yml
artellapipe/config/development/artellapipe-files.yml
artellapipe/config/development/artellapipe-launcher-plugins-dccselector.yml
artellapipe/config/development/artellapipe-launcher.yml
artellapipe/config/development/artellapipe-libs-alembic.yml
artellapipe/config/development/artellapipe-libs-arnold.yml
artellapipe/config/development/artellapipe-libs-artella.yml
artellapipe/config/development/artellapipe-libs-drive.yml
artellapipe/config/development/artellapipe-libs-ffmpeg.yml
artellapipe/config/development/artellapipe-libs-kitsu.yml
artellapipe/config/development/artellapipe-libs-picker.yml
artellapipe/config/development/artellapipe-libs-pyblish.yml
artellapipe/config/development/artellapipe-libs-usd.yml
artellapipe/config/development/artellapipe-media.yml
artellapipe/config/development/artellapipe-menu.yml
artellapipe/config/development/artellapipe-naming.yml
artellapipe/config/development/artellapipe-ocio.yml
artellapipe/config/development/artellapipe-playblasts.yml
artellapipe/config/development/artellapipe-project.yml
artellapipe/config/development/artellapipe-pyblishplugins.yml
artellapipe/config/development/artellapipe-sequences.yml
artellapipe/config/development/artellapipe-shaders.yml
artellapipe/config/development/artellapipe-shots.yml
artellapipe/config/development/artellapipe-tags.yml
artellapipe/config/development/artellapipe-tools-assetslibrary.yml
artellapipe/config/development/artellapipe-tools-assetspublisher.yml
artellapipe/config/development/artellapipe-tools-breakdown.yml
artellapipe/config/development/artellapipe-tools-lightrigsmanager.yml
artellapipe/config/development/artellapipe-tools-modelchecker.yml
artellapipe_config.egg-info/PKG-INFO
artellapipe_config.egg-info/SOURCES.txt
artellapipe_config.egg-info/dependency_links.txt
artellapipe_config.egg-info/not-zip-safe
artellapipe_config.egg-info/requires.txt
artellapipe_config.egg-info/top_level.txt
