Metadata-Version: 2.1
Name: artellapipe-config
Version: 0.0.31
Summary: Artella Pipeline Module that contains project-specific configuration files
Home-page: https://github.com/ArtellaPipe/artellapipe-config
Author: Tomas Poveda
Author-email: tpovedatd@gmail.com
License: MIT
Platform: UNKNOWN
Provides-Extra: dev
Provides-Extra: test
